pyspry/__init__.py
pyspry/base.py
pyspry/keysview/__init__.py
pyspry/keysview/py38.py
pyspry/keysview/py38plus.py
pyspry/nested_dict.py
pyspry/py.typed
pyspry/settings.py
pyspry-1.0.2.dist-info/LICENSE
pyspry-1.0.2.dist-info/METADATA
pyspry-1.0.2.dist-info/WHEEL
pyspry-1.0.2.dist-info/RECORD
