Metadata-Version: 2.1
Name: pyspry
Version: 1.0.2
Summary: A springy little configuration reader
Home-page: https://bfosi.gitlab.io/pyspry/pyspry.html
License: MIT
Author: Bryant Finney
Author-email: finney.bp@gmail.com
Requires-Python: >=3.8,<4.0
Classifier: Intended Audience :: Developers
Classifier: License :: OSI Approved :: MIT License
Classifier: Operating System :: OS Independent
Classifier: Programming Language :: Python :: 3
Classifier: Programming Language :: Python :: 3.8
Classifier: Programming Language :: Python :: 3.9
Classifier: Programming Language :: Python :: 3.10
Classifier: Programming Language :: Python :: 3.11
Classifier: Typing :: Typed
Requires-Dist: pyyaml (>=6.0,<7.0)
Requires-Dist: typing-extensions (>=4.7.1,<5.0.0) ; python_version == "3.8"
Project-URL: Documentation, https://bfosi.gitlab.io/pyspry/index.html
Project-URL: Repository, https://gitlab.com/bfosi/pyspry
